CLOCK/CLOCK-Verilog/Clock-Module/clkm.v
module clock_module(
    input select,
    input hlt,
    input push,
    output reg out
);
  reg astable;
  reg manual;
  
  initial astable = 0;
  always #5 astable = ~astable;

  always@(posedge push) begin
    manual = 1;
    #5;
    manual = 0;
   end

  always@(*) begin
    if (select & ~hlt) begin
        out = astable;
    end else if (~ select & ~ hlt) begin
        out = manual;
    end else if (hlt) begin
        out = 0;
     end
  end

endmodule

CLOCK/CLOCK-Verilog/Clock-Module/clkm_tb.v
`include "clkm.v"

module testbench;

 reg select;
 reg hlt;
 reg push;
 wire out;

 clock_module dut (
    .select(select),
    .hlt(hlt),
    .push(push),
    .out(out)
 );

 initial begin

    $monitor("t = %0t | select = %b | hlt = %b | push = %b | out = %b", $time, select, hlt, push, out);
    $dumpfile("sim.vcd");
    $dumpvars(0, testbench);

    select = 1;
    hlt = 0;
    push = 1;
    #10;
    
    select = 1;
    hlt = 0;
    push = 0;
    #10;

    select = 0;
    hlt = 0;
    push = 0;
    #10;

    select = 0;
    hlt = 0;
    push = 1;
    #10;

    select = 0;
    hlt = 0;
    push = 0;
    #5;

    select = 0;
    hlt = 0;
    push = 1;
    #5;

    select = 0;
    hlt = 1;
    push = 1;
    #10;

    select = 1;
    hlt = 1;
    push = 1;
    #10;

    select = 1;
    hlt = 1;
    push = 0;
    #5;

    select = 1;
    hlt = 1;
    push = 0;
    #5;

    select = 0;
    hlt = 0;
    push = 1;
    #4;

    select = 1;
    hlt = 0;
    push = 0;
    #5;
    
    $display("Simulation Complete!");
    $finish;

  end

endmodule

CLOCK/CLOCK-Verilog/Clock-Module/sim.vcd
$date
	Sun Feb 01 17:01:58 2026
$end
$version
	Icarus Verilog
$end
$timescale
	1s
$end
$scope module testbench $end
$var wire 1 ! out $end
$var reg 1 " hlt $end
$var reg 1 # push $end
$var reg 1 $ select $end
$scope module dut $end
$var wire 1 " hlt $end
$var wire 1 # push $end
$var wire 1 $ select $end
$var reg 1 % astable $end
$var reg 1 & manual $end
$var reg 1 ! out $end
$upscope $end
$upscope $end
$enddefinitions $end
$comment Show the parameter values. $end
$dumpall
$end
#0
$dumpvars
1&
0%
1$
1#
0"
0!
$end
#5
1!
0&
1%
#10
0!
0%
0#
#15
1!
1%
#20
0!
0%
0$
#25
1%
#30
1!
1&
0%
1#
#35
0!
0&
1%
#40
0%
0#
#45
1!
1&
1%
1#
#50
0!
0&
0%
1"
#55
1%
#60
0%
1$
#65
1%
#70
0%
0#
#75
1%
#80
1!
1&
0%
1#
0"
0$
#84
0!
0#
1$
#85
1!
0&
1%
